uvinit/__init__.py
uvinit/copier_workflow.py
uvinit/github_settings.py
uvinit/github_workflow.py
uvinit/main_workflow.py
uvinit/py.typed
uvinit/shell_utils.py
uvinit/uvinit.py
uvinit-0.1.8.dist-info/METADATA
uvinit-0.1.8.dist-info/WHEEL
uvinit-0.1.8.dist-info/entry_points.txt
uvinit-0.1.8.dist-info/licenses/LICENSE
uvinit-0.1.8.dist-info/RECORD
