Metadata-Version: 2.4
Name: uvinit
Version: 0.1.8
Summary: A time-saving CLI to start a new Python project with uv
Project-URL: Repository, https://github.com/jlevy/uvinit
Author-email: jlevy <joshua@cal.berkeley.edu>
License-Expression: MIT
License-File: LICENSE
Classifier: Development Status :: 4 - Beta
Classifier: Intended Audience :: Developers
Classifier: Operating System :: OS Independent
Classifier: Programming Language :: Python
Classifier: Programming Language :: Python :: 3
Classifier: Programming Language :: Python :: 3.11
Classifier: Programming Language :: Python :: 3.12
Classifier: Programming Language :: Python :: 3.13
Classifier: Typing :: Typed
Requires-Python: <4.0,>=3.11
Requires-Dist: copier>=9.6.0
Requires-Dist: prettyfmt>=0.2.1
Requires-Dist: questionary>=2.1.0
Requires-Dist: rich-argparse>=1.7.0
Requires-Dist: rich>=14.0.0
